lockstock_guard/__init__.py
lockstock_guard/cli.py
lockstock_guard/client.py
lockstock_guard/daemon.py
lockstock_guard-1.1.0.dist-info/METADATA
lockstock_guard-1.1.0.dist-info/WHEEL
lockstock_guard-1.1.0.dist-info/entry_points.txt
lockstock_guard-1.1.0.dist-info/top_level.txt
lockstock_guard-1.1.0.dist-info/RECORD
