Metadata-Version: 2.4
Name: lockstock-guard
Version: 1.1.0
Summary: Enterprise secrets daemon for LockStock Protocol - Secure Enclave in Software
Author-email: D3cipher <contact@d3cipher.ai>
License: MIT
Project-URL: Homepage, https://d3cipher.ai
Project-URL: Documentation, https://d3cipher.ai/docs-architecture.html
Project-URL: Repository, https://gitlab.com/deciphergit/lockstock
Project-URL: Issues, https://gitlab.com/deciphergit/lockstock/-/issues
Keywords: secrets,security,daemon,enterprise,lockstock,ai-agents
Classifier: Development Status :: 4 - Beta
Classifier: Intended Audience :: Developers
Classifier: License :: OSI Approved :: MIT License
Classifier: Operating System :: POSIX :: Linux
Classifier: Programming Language :: Python :: 3
Classifier: Programming Language :: Python :: 3.10
Classifier: Programming Language :: Python :: 3.11
Classifier: Programming Language :: Python :: 3.12
Classifier: Programming Language :: Python :: 3.13
Classifier: Topic :: Security
Classifier: Topic :: System :: Systems Administration
Requires-Python: >=3.10
Requires-Dist: cryptography>=41.0.0
Requires-Dist: liberty-secrets>=1.1.0
Requires-Dist: requests>=2.25.0
Provides-Extra: dev
Requires-Dist: pytest>=7.0.0; extra == "dev"
Requires-Dist: pytest-asyncio>=0.21.0; extra == "dev"
